setup.py
xyz_infinite.egg-info/PKG-INFO
xyz_infinite.egg-info/SOURCES.txt
xyz_infinite.egg-info/dependency_links.txt
xyz_infinite.egg-info/requires.txt
xyz_infinite.egg-info/top_level.txt
xyz_infinite.egg-info/zip-safe
xyz_tibet/__init__.py
xyz_tibet/__main__.py
xyz_tibet/utils/__init__.py
xyz_tibet/utils/control_utils.py
xyz_tibet/utils/datetime_utils.py
xyz_tibet/utils/encoding_utils.py
xyz_tibet/utils/enumeration.py
xyz_tibet/utils/file_utils.py
xyz_tibet/utils/progress_utils.py
xyz_tibet/utils/exception/__init__.py
xyz_tibet/utils/exception/custom_exceptions.py