Metadata-Version: 1.0
Name: xyz-infinite
Version: 1.0.0
Summary: a library for save your time
Home-page: https://github.com/wxnacy/wwx
Author: changping
Author-email: xiaoyao_cp@163.com
License: MIT License
Keywords: wx
Platform: any
